{
  "project_info": {
    "project_number": "88294615937",
    "project_id": "radio-app-9bb21",
    "storage_bucket": "radio-app-9bb21.appspot.com"
  },
  "client": [
    {
      "client_info": {
        "mobilesdk_app_id": "1:88294615937:android:e9d027ca5f3e8f78e55680",
        "android_client_info": {
          "package_name": "com.example.radio"
        }
      },
      "oauth_client": [],
      "api_key": [
        {
          "current_key": "AIzaSyDSG28kOgRc4awdhiQxRV-uWwU5dENJneA"
        }
      ],
      "services": {
        "appinvite_service": {
          "other_platform_oauth_client": []
        }
      }
    }
  ],
  "configuration_version": "1"
}